libevdev/__init__.py
libevdev/__init__.pyi
libevdev/_clib.py
libevdev/const.py
libevdev/device.py
libevdev/event.py
libevdev-0.13.dist-info/METADATA
libevdev-0.13.dist-info/WHEEL
libevdev-0.13.dist-info/licenses/COPYING
libevdev-0.13.dist-info/RECORD
