Metadata-Version: 2.4
Name: libevdev
Version: 0.13
Summary: Python wrapper for libevdev
Project-URL: Homepage, https://gitlab.freedesktop.org/libevdev/python-libevdev
Project-URL: Documentation, https://python-libevdev.readthedocs.io/en/latest/
Project-URL: Repository, https://gitlab.freedesktop.org/libevdev/python-libevdev
Author-email: Peter Hutterer <peter.hutterer@who-t.net>
License: MIT
License-File: COPYING
Keywords: evdev,input,libevdev,uinput
Classifier: Development Status :: 4 - Beta
Classifier: Intended Audience :: Developers
Classifier: License :: OSI Approved :: MIT License
Classifier: Programming Language :: Python :: 3
Classifier: Topic :: Software Development
Requires-Python: >=3.9
